[
    {
        "student_class": "1D",
        "student_name": "Aya Maaswinkel",
        "student_number": 2464483
    },
    {
        "student_class": "1E",
        "student_name": "Frederique van der Sloot-Blaak",
        "student_number": 4990264
    },
    {
        "student_class": "1E",
        "student_name": "Nina Mansveld",
        "student_number": 3558792
    },
    {
        "student_class": "1C",
        "student_name": "Bryan Kremer",
        "student_number": 2317948
    },
    {
        "student_class": "1A",
        "student_name": "Ecrin Doesburg",
        "student_number": 7799523
    },
    {
        "student_class": "1E",
        "student_name": "Nathan Olykan-van Wijland",
        "student_number": 2338278
    },
    {
        "student_class": "1D",
        "student_name": "Sylvie Spiker",
        "student_number": 2095137
    },
    {
        "student_class": "1A",
        "student_name": "Dylano Laffray",
        "student_number": 7535802
    },
    {
        "student_class": "1C",
        "student_name": "Mette Ansems",
        "student_number": 2603543
    },
    {
        "student_class": "1E",
        "student_name": "Tobias Haengreve",
        "student_number": 2071260
    },
    {
        "student_class": "1B",
        "student_name": "Rowan Vignon",
        "student_number": 9817946
    },
    {
        "student_class": "1B",
        "student_name": "Floor van der Horst-Timmermans",
        "student_number": 1411164
    },
    {
        "student_class": "1D",
        "student_name": "Fenne van Praagh-Bruggeman",
        "student_number": 5499173
    },
    {
        "student_class": "1D",
        "student_name": "Dylano Blom-Blewanus",
        "student_number": 3425925
    },
    {
        "student_class": "1D",
        "student_name": "Liz Ouwerkerk",
        "student_number": 2704622
    },
    {
        "student_class": "1C",
        "student_name": "Jelle Van Bragt",
        "student_number": 1852720
    },
    {
        "student_class": "1A",
        "student_name": "Evi van de Ven",
        "student_number": 2232772
    },
    {
        "student_class": "1D",
        "student_name": "Merel Simons",
        "student_number": 6786988
    },
    {
        "student_class": "1D",
        "student_name": "Amira van Bergen-Texier",
        "student_number": 7028399
    },
    {
        "student_class": "1E",
        "student_name": "Morris van Bovene-Verbeek",
        "student_number": 2321500
    },
    {
        "student_class": "1D",
        "student_name": "Danique Velderman",
        "student_number": 8124341
    },
    {
        "student_class": "1C",
        "student_name": "Alyssa Vial-Huijzing",
        "student_number": 4965788
    },
    {
        "student_class": "1E",
        "student_name": "Stan Spies",
        "student_number": 8831873
    },
    {
        "student_class": "1B",
        "student_name": "Lucas Mansveld-de la Fleche",
        "student_number": 1182671
    },
    {
        "student_class": "1B",
        "student_name": "Wouter van Oostendorp",
        "student_number": 4737466
    },
    {
        "student_class": "1D",
        "student_name": "Riley Wright",
        "student_number": 6838504
    },
    {
        "student_class": "1A",
        "student_name": "Jelte West-Franci\u00eb, van",
        "student_number": 2467615
    },
    {
        "student_class": "1B",
        "student_name": "Evie Bolkesteijn",
        "student_number": 6840850
    },
    {
        "student_class": "1D",
        "student_name": "Norah van der Kint",
        "student_number": 2824197
    },
    {
        "student_class": "1B",
        "student_name": "Yara van Engelen",
        "student_number": 8826007
    },
    {
        "student_class": "1A",
        "student_name": "Fien Phillipsen",
        "student_number": 5074078
    },
    {
        "student_class": "1A",
        "student_name": "Imran van Gent-de Bock",
        "student_number": 1122607
    },
    {
        "student_class": "1D",
        "student_name": "Oscar Wooning-Lathrope",
        "student_number": 1772998
    },
    {
        "student_class": "1E",
        "student_name": "Alex Muijs",
        "student_number": 6777308
    },
    {
        "student_class": "1E",
        "student_name": "Zara Volcke",
        "student_number": 3876648
    },
    {
        "student_class": "1A",
        "student_name": "Ivy van Grondelle",
        "student_number": 3351603
    },
    {
        "student_class": "1D",
        "student_name": "Fien Meijer",
        "student_number": 2237994
    },
    {
        "student_class": "1A",
        "student_name": "Maaike van Asten",
        "student_number": 3931563
    },
    {
        "student_class": "1B",
        "student_name": "Tyler Koster",
        "student_number": 5508372
    },
    {
        "student_class": "1E",
        "student_name": "Dex Hulskes-van den Oever",
        "student_number": 3903526
    },
    {
        "student_class": "1A",
        "student_name": "Rens van de Plas",
        "student_number": 7549397
    },
    {
        "student_class": "1B",
        "student_name": "Rayan Dachgelt",
        "student_number": 5973704
    },
    {
        "student_class": "1E",
        "student_name": "Ryan Westermann",
        "student_number": 8488333
    },
    {
        "student_class": "1C",
        "student_name": "Dave de Pauw-Levesque",
        "student_number": 6541270
    },
    {
        "student_class": "1C",
        "student_name": "Rowan Everde",
        "student_number": 3675312
    },
    {
        "student_class": "1D",
        "student_name": "Noud Ellis",
        "student_number": 5682228
    },
    {
        "student_class": "1D",
        "student_name": "Evy Goudriaan",
        "student_number": 1232429
    },
    {
        "student_class": "1C",
        "student_name": "Jenna de Reede-Unruoch Hunerik",
        "student_number": 1145590
    },
    {
        "student_class": "1D",
        "student_name": "Anna Winters",
        "student_number": 6407271
    },
    {
        "student_class": "1C",
        "student_name": "Lisanne Janssen",
        "student_number": 9433357
    },
    {
        "student_class": "1C",
        "student_name": "Michael van der Ven",
        "student_number": 8179910
    },
    {
        "student_class": "1E",
        "student_name": "Benjamin Rijn-van de Brink",
        "student_number": 6031351
    },
    {
        "student_class": "1D",
        "student_name": "Lara Jacobs-van Leeuwen",
        "student_number": 2443681
    },
    {
        "student_class": "1A",
        "student_name": "Jan Rackham-van Mil",
        "student_number": 9293310
    },
    {
        "student_class": "1B",
        "student_name": "Jente Henric van den Nuwenhuse",
        "student_number": 6541371
    },
    {
        "student_class": "1A",
        "student_name": "Maartje Lansink-Otto",
        "student_number": 8239435
    },
    {
        "student_class": "1C",
        "student_name": "Isabella Spreeuw-Slaetsdochter",
        "student_number": 8931645
    },
    {
        "student_class": "1E",
        "student_name": "Isabel Molen-Kriens",
        "student_number": 4270903
    },
    {
        "student_class": "1B",
        "student_name": "Senna Vink-de Hoogh",
        "student_number": 2008557
    },
    {
        "student_class": "1C",
        "student_name": "Sophie Simonis-van Salm",
        "student_number": 3518243
    },
    {
        "student_class": "1D",
        "student_name": "Puck B\u00f6kenkamp-Brouwer",
        "student_number": 6657465
    },
    {
        "student_class": "1B",
        "student_name": "Philip Passchiers",
        "student_number": 9782420
    },
    {
        "student_class": "1B",
        "student_name": "Danique de Bock",
        "student_number": 9688523
    },
    {
        "student_class": "1A",
        "student_name": "Kai Boeser",
        "student_number": 5481912
    },
    {
        "student_class": "1A",
        "student_name": "Isabel van Breugel",
        "student_number": 7263063
    },
    {
        "student_class": "1B",
        "student_name": "Mats Stettyn",
        "student_number": 4219731
    },
    {
        "student_class": "1B",
        "student_name": "Aiden Arnold",
        "student_number": 9037811
    },
    {
        "student_class": "1D",
        "student_name": "Jacob van der Loo",
        "student_number": 2926899
    },
    {
        "student_class": "1E",
        "student_name": "Jules van Verdun",
        "student_number": 9284742
    },
    {
        "student_class": "1C",
        "student_name": "Ise van den Wittenboer",
        "student_number": 4168869
    },
    {
        "student_class": "1B",
        "student_name": "Bas Ketting",
        "student_number": 7512863
    },
    {
        "student_class": "1B",
        "student_name": "Jill Perck",
        "student_number": 7332019
    },
    {
        "student_class": "1D",
        "student_name": "Silke de Kok",
        "student_number": 7278713
    },
    {
        "student_class": "1C",
        "student_name": "Colin van Goerle",
        "student_number": 7123697
    },
    {
        "student_class": "1C",
        "student_name": "Sebastiaan de Vries",
        "student_number": 8475295
    },
    {
        "student_class": "1A",
        "student_name": "Mare Mulder",
        "student_number": 7647427
    },
    {
        "student_class": "1B",
        "student_name": "Suze de Kale",
        "student_number": 7383264
    },
    {
        "student_class": "1D",
        "student_name": "Nadia Eerden",
        "student_number": 6625414
    },
    {
        "student_class": "1C",
        "student_name": "Nathan Oosterhout",
        "student_number": 1205529
    },
    {
        "student_class": "1D",
        "student_name": "Mason Verkade-Bouhuizen",
        "student_number": 6409824
    },
    {
        "student_class": "1A",
        "student_name": "Ivy Hoogers",
        "student_number": 3324720
    },
    {
        "student_class": "1B",
        "student_name": "Livia Blaak",
        "student_number": 2891432
    },
    {
        "student_class": "1A",
        "student_name": "Jinthe Langevoort",
        "student_number": 5715118
    },
    {
        "student_class": "1D",
        "student_name": "Nina le Matelot-Jansdr",
        "student_number": 5251171
    },
    {
        "student_class": "1C",
        "student_name": "Quinty Chotzen",
        "student_number": 8167154
    },
    {
        "student_class": "1A",
        "student_name": "Evie Fortuyn",
        "student_number": 7804917
    },
    {
        "student_class": "1A",
        "student_name": "Kyan Guit",
        "student_number": 5758538
    },
    {
        "student_class": "1B",
        "student_name": "Rosa Pauwels",
        "student_number": 6548779
    },
    {
        "student_class": "1E",
        "student_name": "Sam die Pelser-Steenbeek",
        "student_number": 2554236
    },
    {
        "student_class": "1B",
        "student_name": "Rayan Pieters van der Maes",
        "student_number": 6421308
    },
    {
        "student_class": "1E",
        "student_name": "Bo Kloppert",
        "student_number": 1964008
    },
    {
        "student_class": "1A",
        "student_name": "Benjamin Strijker",
        "student_number": 6052614
    },
    {
        "student_class": "1B",
        "student_name": "Nynke Ehlert",
        "student_number": 1154367
    },
    {
        "student_class": "1D",
        "student_name": "Lisanne Lucas-Wagenvoort",
        "student_number": 4619837
    },
    {
        "student_class": "1D",
        "student_name": "Nynke van Hamaland",
        "student_number": 9103907
    },
    {
        "student_class": "1B",
        "student_name": "Melissa van de Noordmark",
        "student_number": 1382725
    },
    {
        "student_class": "1D",
        "student_name": "Isis Dijkman-van den Velden",
        "student_number": 9215154
    },
    {
        "student_class": "1B",
        "student_name": "Jim Hanegraaff",
        "student_number": 7357386
    },
    {
        "student_class": "1E",
        "student_name": "Jip Van Bragt",
        "student_number": 3307255
    }
]